navig8r/__init__.py
navig8r/images/logo.png
navig8r/navig8r.py
navig8r/util.py
navig8r-0.1.3.dist-info/LICENSE
navig8r-0.1.3.dist-info/WHEEL
navig8r-0.1.3.dist-info/METADATA
navig8r-0.1.3.dist-info/entry_points.txt
navig8r-0.1.3.dist-info/RECORD
